AUTHORS
LICENSE
README.rst
setup.cfg
setup.py
kafy/__init__.py
kafy/backend_internal.py
kafy/backend_shared.py
kafy/backend_youtube_dl.py
kafy/channel.py
kafy/g.py
kafy/jsinterp.py
kafy/kafy.py
kafy/playlist.py
kafy/util.py
kafy.egg-info/PKG-INFO
kafy.egg-info/SOURCES.txt
kafy.egg-info/dependency_links.txt
kafy.egg-info/requires.txt
kafy.egg-info/top_level.txt
scripts/ytdl