Metadata-Version: 2.1
Name: kafy
Version: 1.1
Summary: Retrieve YouTube content and metadata
Home-page: https://github.com/SenuGamerBoy/Kafay/
Author: SenuGamerBoy
Author-email: shamilasamarakoon14@gmail.com
License: LGPLv3
Download-URL: https://github.com/SenuGamerBoy/Kafay/tags
Keywords: kafy,API,YouTube,youtube,download,video
Platform: UNKNOWN
Classifier: License :: OSI Approved :: GNU Lesser General Public License v3 (LGPLv3)
Classifier: Operating System :: POSIX :: Linux
Classifier: Operating System :: MacOS
Classifier: Operating System :: MacOS :: MacOS 9
Classifier: Operating System :: MacOS :: MacOS X
Classifier: Operating System :: Microsoft
Classifier: Operating System :: Microsoft :: Windows :: Windows 7
Classifier: Operating System :: Microsoft :: Windows :: Windows XP
Classifier: Operating System :: Microsoft :: Windows :: Windows Vista
Classifier: Programming Language :: Python
Classifier: Programming Language :: Python :: 3.3
Classifier: Programming Language :: Python :: 3.4
Classifier: Intended Audience :: Developers
Classifier: Development Status :: 5 - Production/Stable
Classifier: Topic :: Multimedia :: Sound/Audio :: Capture/Recording
Classifier: Topic :: Utilities
Classifier: Topic :: Multimedia :: Video
Classifier: Topic :: Internet :: WWW/HTTP
Provides-Extra: youtube-dl-backend
License-File: LICENSE
License-File: AUTHORS
